[1,0,0,[["cc.JsonAsset",["_name","json"],1]],[[0,0,1,3]],[[0,"20575",{"id":"62b42d943dd1931da84a8474","created_at":"2022-06-23T09:08:36.26Z","updated_at":"2022-07-01T08:26:18.423Z","map_id":20575,"map_data":"{\"widthNum\":8,\"heightNum\":10,\"levelKey\":20575,\"blockTypeData\":{\"16\":2,\"17\":2,\"25\":3,\"35\":3},\"levelData\":{\"1\":[{\"id\":\"1-16-8\",\"type\":0,\"rolNum\":16,\"rowNum\":8,\"layerNum\":1,\"moldType\":1,\"blockNode\":null},{\"id\":\"1-16-16\",\"type\":0,\"rolNum\":16,\"rowNum\":16,\"layerNum\":1,\"moldType\":1,\"blockNode\":null},{\"id\":\"1-16-24\",\"type\":0,\"rolNum\":16,\"rowNum\":24,\"layerNum\":1,\"moldType\":1,\"blockNode\":null},{\"id\":\"1-24-24\",\"type\":0,\"rolNum\":24,\"rowNum\":24,\"layerNum\":1,\"moldType\":1,\"blockNode\":null},{\"id\":\"1-24-32\",\"type\":0,\"rolNum\":24,\"rowNum\":32,\"layerNum\":1,\"moldType\":1,\"blockNode\":null},{\"id\":\"1-40-8\",\"type\":0,\"rolNum\":40,\"rowNum\":8,\"layerNum\":1,\"moldType\":1,\"blockNode\":null},{\"id\":\"1-40-16\",\"type\":0,\"rolNum\":40,\"rowNum\":16,\"layerNum\":1,\"moldType\":1,\"blockNode\":null},{\"id\":\"1-40-24\",\"type\":0,\"rolNum\":40,\"rowNum\":24,\"layerNum\":1,\"moldType\":1,\"blockNode\":null},{\"id\":\"1-32-24\",\"type\":0,\"rolNum\":32,\"rowNum\":24,\"layerNum\":1,\"moldType\":1,\"blockNode\":null},{\"id\":\"1-32-32\",\"type\":0,\"rolNum\":32,\"rowNum\":32,\"layerNum\":1,\"moldType\":1,\"blockNode\":null},{\"id\":\"1-24-48\",\"type\":0,\"rolNum\":24,\"rowNum\":48,\"layerNum\":1,\"moldType\":2,\"blockNode\":null},{\"id\":\"1-32-48\",\"type\":0,\"rolNum\":32,\"rowNum\":48,\"layerNum\":1,\"moldType\":2,\"blockNode\":null}],\"2\":[{\"id\":\"2-20-12\",\"type\":0,\"rolNum\":20,\"rowNum\":12,\"layerNum\":2,\"moldType\":1,\"blockNode\":null},{\"id\":\"2-20-20\",\"type\":0,\"rolNum\":20,\"rowNum\":20,\"layerNum\":2,\"moldType\":1,\"blockNode\":null},{\"id\":\"2-36-12\",\"type\":0,\"rolNum\":36,\"rowNum\":12,\"layerNum\":2,\"moldType\":1,\"blockNode\":null},{\"id\":\"2-36-20\",\"type\":0,\"rolNum\":36,\"rowNum\":20,\"layerNum\":2,\"moldType\":1,\"blockNode\":null},{\"id\":\"2-28-20\",\"type\":0,\"rolNum\":28,\"rowNum\":20,\"layerNum\":2,\"moldType\":1,\"blockNode\":null},{\"id\":\"2-24-28\",\"type\":0,\"rolNum\":24,\"rowNum\":28,\"layerNum\":2,\"moldType\":1,\"blockNode\":null},{\"id\":\"2-32-28\",\"type\":0,\"rolNum\":32,\"rowNum\":28,\"layerNum\":2,\"moldType\":1,\"blockNode\":null},{\"id\":\"2-24-49\",\"type\":0,\"rolNum\":24,\"rowNum\":49,\"layerNum\":2,\"moldType\":2,\"blockNode\":null},{\"id\":\"2-32-49\",\"type\":0,\"rolNum\":32,\"rowNum\":49,\"layerNum\":2,\"moldType\":2,\"blockNode\":null}],\"3\":[{\"id\":\"3-24-24\",\"type\":0,\"rolNum\":24,\"rowNum\":24,\"layerNum\":3,\"moldType\":1,\"blockNode\":null},{\"id\":\"3-32-24\",\"type\":0,\"rolNum\":32,\"rowNum\":24,\"layerNum\":3,\"moldType\":1,\"blockNode\":null},{\"id\":\"3-20-16\",\"type\":0,\"rolNum\":20,\"rowNum\":16,\"layerNum\":3,\"moldType\":1,\"blockNode\":null},{\"id\":\"3-36-16\",\"type\":0,\"rolNum\":36,\"rowNum\":16,\"layerNum\":3,\"moldType\":1,\"blockNode\":null},{\"id\":\"3-24-50\",\"type\":0,\"rolNum\":24,\"rowNum\":50,\"layerNum\":3,\"moldType\":2,\"blockNode\":null},{\"id\":\"3-32-50\",\"type\":0,\"rolNum\":32,\"rowNum\":50,\"layerNum\":3,\"moldType\":2,\"blockNode\":null}],\"4\":[{\"id\":\"4-24-51\",\"type\":0,\"rolNum\":24,\"rowNum\":51,\"layerNum\":4,\"moldType\":2,\"blockNode\":null},{\"id\":\"4-32-51\",\"type\":0,\"rolNum\":32,\"rowNum\":51,\"layerNum\":4,\"moldType\":2,\"blockNode\":null},{\"id\":\"4-28-24\",\"type\":0,\"rolNum\":28,\"rowNum\":24,\"layerNum\":4,\"moldType\":1,\"blockNode\":null}]}}"}]],0,0,[],[],[]]